mkv2cast/__init__.py
mkv2cast/__main__.py
mkv2cast/cli.py
mkv2cast/config.py
mkv2cast/converter.py
mkv2cast/history.py
mkv2cast/i18n.py
mkv2cast/integrity.py
mkv2cast/json_progress.py
mkv2cast/notifications.py
mkv2cast/pipeline.py
mkv2cast/watcher.py
mkv2cast/locales/de/LC_MESSAGES/mkv2cast.mo
mkv2cast/locales/de/LC_MESSAGES/mkv2cast.po
mkv2cast/locales/en/LC_MESSAGES/mkv2cast.mo
mkv2cast/locales/en/LC_MESSAGES/mkv2cast.po
mkv2cast/locales/es/LC_MESSAGES/mkv2cast.mo
mkv2cast/locales/es/LC_MESSAGES/mkv2cast.po
mkv2cast/locales/fr/LC_MESSAGES/mkv2cast.mo
mkv2cast/locales/fr/LC_MESSAGES/mkv2cast.po
mkv2cast/locales/it/LC_MESSAGES/mkv2cast.mo
mkv2cast/locales/it/LC_MESSAGES/mkv2cast.po
mkv2cast/ui/__init__.py
mkv2cast/ui/legacy_ui.py
mkv2cast/ui/rich_ui.py
mkv2cast/ui/simple_rich.py
mkv2cast-1.2.9.post2.dist-info/METADATA
mkv2cast-1.2.9.post2.dist-info/WHEEL
mkv2cast-1.2.9.post2.dist-info/entry_points.txt
mkv2cast-1.2.9.post2.dist-info/licenses/LICENSE
mkv2cast-1.2.9.post2.dist-info/RECORD
