Metadata-Version: 2.4
Name: mkv2cast
Version: 1.2.9.post2
Summary: Smart MKV to Chromecast-compatible converter with hardware acceleration
Project-URL: Homepage, https://github.com/voldardard/mkv2cast
Project-URL: Documentation, https://voldardard.github.io/mkv2cast
Project-URL: Repository, https://github.com/voldardard/mkv2cast
Project-URL: Issues, https://github.com/voldardard/mkv2cast/issues
Project-URL: Changelog, https://github.com/voldardard/mkv2cast/blob/main/CHANGELOG.md
Author: voldardard
License-Expression: GPL-3.0-or-later
License-File: LICENSE
Keywords: chromecast,converter,ffmpeg,mkv,qsv,transcoding,vaapi,video
Classifier: Development Status :: 5 - Production/Stable
Classifier: Environment :: Console
Classifier: Intended Audience :: End Users/Desktop
Classifier: License :: OSI Approved :: GNU General Public License v3 (GPLv3)
Classifier: Operating System :: POSIX :: Linux
Classifier: Programming Language :: Python :: 3
Classifier: Programming Language :: Python :: 3.8
Classifier: Programming Language :: Python :: 3.9
Classifier: Programming Language :: Python :: 3.10
Classifier: Programming Language :: Python :: 3.11
Classifier: Programming Language :: Python :: 3.12
Classifier: Topic :: Multimedia :: Video :: Conversion
Requires-Python: >=3.8
Provides-Extra: dev
Requires-Dist: mypy>=1.0; extra == 'dev'
Requires-Dist: myst-parser>=2.0.0; extra == 'dev'
Requires-Dist: pytest-cov>=4.0; extra == 'dev'
Requires-Dist: pytest>=7.0; extra == 'dev'
Requires-Dist: ruff>=0.1.0; extra == 'dev'
Requires-Dist: sphinx-rtd-theme>=2.0; extra == 'dev'
Requires-Dist: sphinx>=7.0; extra == 'dev'
Provides-Extra: full
Requires-Dist: plyer>=2.1.0; extra == 'full'
Requires-Dist: rich>=13.0.0; extra == 'full'
Requires-Dist: tomli>=2.0.0; (python_version < '3.11') and extra == 'full'
Requires-Dist: watchdog>=3.0.0; extra == 'full'
Provides-Extra: notifications
Requires-Dist: plyer>=2.1.0; extra == 'notifications'
Provides-Extra: rich
Requires-Dist: rich>=13.0.0; extra == 'rich'
Provides-Extra: watch
Requires-Dist: watchdog>=3.0.0; extra == 'watch'
